[
  {"imgsrc":"project/images/pic_01.jpg ","imgb":"project/images/pic_01_b.jpg","desc":"Darina"},
  {"imgsrc":"project/images/pic_02.jpg","imgb":"project/images/pic_02_b.jpg","desc":"短发"},
  {"imgsrc":"project/images/pic_03.jpg","imgb":"project/images/pic_03_b.jpg","desc":"那些等待里的时光"},
  {"imgsrc":"project/images/pic_04.jpg","imgb":"project/images/pic_04_b.jpg","desc":"唯有时光不可辜负"},
  {"imgsrc":"project/images/pic_05.jpg","imgb":"project/images/pic_05_b.jpg","desc":"雨夜"},
  {"imgsrc":"project/images/pic_06.jpg","imgb":"project/images/pic_06_b.jpg","desc":"Perfectly"},
  {"imgsrc":"project/images/pic_07.jpg","imgb":"project/images/pic_07_b.jpg","desc":"寒冬里的夏日少女"},
  {"imgsrc":"project/images/pic_08.jpg","imgb":"project/images/pic_08_b.jpg","desc":"  Blue "},
  {"imgsrc":"project/images/pic_09.jpg","imgb":"project/images/pic_09_b.jpg","desc":"佳人"},
  {"imgsrc":"project/images/pic_10.jpg","imgb":"project/images/pic_10_b.jpg","desc":"在路上"},
  {"imgsrc":"project/images/pic_11.jpg","imgb":"project/images/pic_11_b.jpg","desc":"吹呀吹，吹个蒲公英"},
  {"imgsrc":"project/images/pic_12.jpg","imgb":"project/images/pic_12_b.jpg","desc":"入戏"},
  {"imgsrc":"project/images/pic_13.jpg","imgb":"project/images/pic_13_b.jpg","desc":"爱宠日记"},
  {"imgsrc":"project/images/pic_14.jpg","imgb":"project/images/pic_14_b.jpg","desc":"拥抱大棉花糖"},
  {"imgsrc":"project/images/pic_15.jpg","imgb":"project/images/pic_15_b.jpg","desc":"~森系子猫物语~"}
]